rankingTool/GUI.py
rankingTool/Proposal.py
rankingTool/Ranking.py
rankingTool/Review.py
rankingTool/Reviewer.py
rankingTool/__init__.py
rankingTool/filter.py
rankingTool/legend_window.py
rankingTool/proposal_box.py
rankingTool-1.0.dist-info/LICENSE.txt
rankingTool-1.0.dist-info/METADATA
rankingTool-1.0.dist-info/WHEEL
rankingTool-1.0.dist-info/top_level.txt
rankingTool-1.0.dist-info/RECORD
