Metadata-Version: 2.1
Name: rankingTool
Version: 1.0
Summary: This is the first version of the package of Rankings UI, which helps visualize the rankings and ratings for comparison.
Home-page: https://github.com/mk322/Rankings-UI
Author: Haoqiang Kang
Author-email: haoqik@cs.washington.edu
License: MIT
Keywords: GUI,Rankings,Ratings
License-File: LICENSE.txt
Requires-Dist: toml
Requires-Dist: pandas
Requires-Dist: numpy
Requires-Dist: xlrd (>=1.0.0)
